aiia_sdk/__init__.py
aiia_sdk/aiia_sdk.py
aiia_sdk/aiia_sdk_v3.py
aiia_sdk/auto_interceptor.py
aiia_sdk/auto_interceptor_v2.py
aiia_sdk/cli.py
aiia_sdk/middleware_django.py
aiia_sdk/middleware_fastapi.py
aiia_sdk/middleware_flask.py
aiia_sdk/numpy_utils.py
aiia_sdk/performance_optimizations.py
aiia_sdk/persistent_queue.py
aiia_sdk/semantic_detect_action_new.py
aiia_sdk/semantic_singleton.py
aiia_sdk/utils.py
aiia_sdk/cache/actions_cache.json
aiia_sdk/data/actions.json
aiia_sdk/data/aiia_actions_v1.0.json
aiia_sdk-0.3.4.dist-info/licenses/LICENSE
aiia_sdk-0.3.4.dist-info/METADATA
aiia_sdk-0.3.4.dist-info/WHEEL
aiia_sdk-0.3.4.dist-info/entry_points.txt
aiia_sdk-0.3.4.dist-info/top_level.txt
aiia_sdk-0.3.4.dist-info/RECORD
