Metadata-Version: 2.4
Name: aiia-sdk
Version: 0.3.4
Summary: Official AIIA SDK for logging AI actions with legal and operational traceability - 100% Plug & Play
Author: AIIA
Author-email: javier.sanchez@aiiatrace.com
Classifier: Development Status :: 4 - Beta
Classifier: Intended Audience :: Developers
Classifier: License :: OSI Approved :: MIT License
Classifier: Programming Language :: Python :: 3
Classifier: Programming Language :: Python :: 3.8
Classifier: Topic :: Software Development :: Libraries
Classifier: Topic :: Scientific/Engineering :: Artificial Intelligence
Requires-Python: >=3.8
License-File: LICENSE
Requires-Dist: requests>=2.25.0
Requires-Dist: python-dotenv>=0.19.0
Requires-Dist: cryptography>=39.0.0
Requires-Dist: tldextract>=3.1.0
Provides-Extra: semantic
Requires-Dist: sentence-transformers>=2.2.2; extra == "semantic"
Requires-Dist: transformers>=4.0.0; extra == "semantic"
Dynamic: author
Dynamic: author-email
Dynamic: classifier
Dynamic: description
Dynamic: description-content-type
Dynamic: license-file
Dynamic: provides-extra
Dynamic: requires-dist
Dynamic: requires-python
Dynamic: summary
